LICENSE
MANIFEST.in
README.rst
setup.py
petfinder/__init__.py
petfinder/client.py
petfinder/exceptions.py
petfinder/version.py
petfinder.egg-info/PKG-INFO
petfinder.egg-info/SOURCES.txt
petfinder.egg-info/dependency_links.txt
petfinder.egg-info/requires.txt
petfinder.egg-info/top_level.txt
tests/__init__.py
tests/api_details.blank.py
tests/api_details.py
tests/api_tests.py