Metadata-Version: 1.1
Name: petfinder
Version: 0.3
Summary: A simple wrapper around Petfinder's API
Home-page: https://github.com/gtaylor/petfinder-api
Author: Greg Taylor
Author-email: gtaylor@gc-taylor.com
License: BSD
Platform: UNKNOWN
Classifier: Development Status :: 4 - Beta
Classifier: Intended Audience :: Developers
Classifier: Natural Language :: English
Classifier: License :: OSI Approved :: BSD License
Classifier: Programming Language :: Python
Classifier: Programming Language :: Python :: 2.7
